jsonalias/__init__.py
jsonalias/py.typed
jsonalias-0.1.2.dist-info/LICENSE
jsonalias-0.1.2.dist-info/WHEEL
jsonalias-0.1.2.dist-info/METADATA
jsonalias-0.1.2.dist-info/RECORD
